crimson/anytree_extension/__init__.py
crimson/anytree_extension/collapsor/__init__.py
crimson/anytree_extension/collapsor/base.py
crimson/anytree_extension/conterver/__init__.py
crimson/anytree_extension/filter/__init__.py
crimson/anytree_extension/finder/__init__.py
crimson/anytree_extension/patch/nodemixin.py
crimson/anytree_extension/types/fn.py
crimson/anytree_extension/types/node.py
crimson/anytree_extension/unique_node/__init__.py
crimson/anytree_extension/utils/arranger.py
crimson/anytree_extension/utils/printer.py
crimson_anytree_extension-0.1.3.dist-info/licenses/LICENSE
crimson_anytree_extension-0.1.3.dist-info/METADATA
crimson_anytree_extension-0.1.3.dist-info/WHEEL
crimson_anytree_extension-0.1.3.dist-info/top_level.txt
crimson_anytree_extension-0.1.3.dist-info/RECORD
